puissance4C.py
puissance4C-0.0.2.dist-info/LICENCE
puissance4C-0.0.2.dist-info/METADATA
puissance4C-0.0.2.dist-info/WHEEL
puissance4C-0.0.2.dist-info/top_level.txt
puissance4C-0.0.2.dist-info/RECORD
