Metadata-Version: 2.1
Name: puissance4C
Version: 0.0.2
Summary: Puissance4C est un module puissance 4 en console et en     couleur, à jouer à 2.
Home-page: https://framagit.org/zenjo/puissance4c/wikis/home
Author: Robert Sebille
Author-email: robert@sebille.name
Maintainer: Robert Sebille
Maintainer-email: robert@sebille.name
License: GNU GPL
Download-URL: https://framagit.org/zenjo/puissance4c/tree/master
Platform: UNKNOWN
Classifier: Programming Language :: Python :: 3
Classifier: License :: OSI Approved :: GNU General Public License (GPL)
Classifier: Operating System :: OS Independent
